pydtr/__init__.py
pydtr/version.py
pydtr/iqlearn/__init__.py
pydtr/iqlearn/base.py
pydtr/iqlearn/regression.py
pydtr-0.0.2.dist-info/LICENSE
pydtr-0.0.2.dist-info/METADATA
pydtr-0.0.2.dist-info/WHEEL
pydtr-0.0.2.dist-info/top_level.txt
pydtr-0.0.2.dist-info/RECORD
