Metadata-Version: 2.1
Name: pydtr
Version: 0.0.2
Summary: Python library of Dynamic Treatment Regimes
Home-page: https://github.com/fullflu/pydtr
Author: fullflu
Author-email: k.takayama0902@gmail.com
License: BSD
Keywords: dynamic treatment regimes,reinforcement learning,dtr
Platform: UNKNOWN
Classifier: Topic :: Scientific/Engineering :: Artificial Intelligence
Classifier: License :: OSI Approved :: BSD License
Classifier: Programming Language :: Python :: 3
Classifier: Programming Language :: Python :: 3.6
Requires-Dist: pandas (>=1.1.2)
Requires-Dist: scikit-learn (>=0.23.2)
Requires-Dist: numpy (>=1.19.2)
Requires-Dist: statsmodels (>=0.12.0)
